iftest/rom.v
module rom (
    input wire ce_i,
    input wire[31:0] addr_i,
    output reg[31:0] inst_o
);
    reg[31:0] rom[63:0];

    initial $readmemh("data/rom.data", rom);
    integer i;
    initial begin
    $display("data:");
        for(i=0;i<9;i=i+1)
            $display("%d:%h",i,rom[i]);   
    end
    
    always @(*) begin
        if(ce_i) begin
            inst_o = rom[addr_i];
        end else begin
            inst_o = 32'h0;
        end
    end
endmodule

iftest/defines.v
`define CpuResetAddr 32'h0

`define RstEnable 1'b0
`define RstDisable 1'b1
`define ZeroWord 32'h0
`define ZeroReg 5'h0
`define WriteEnable 1'b1
`define WriteDisable 1'b0
`define ReadEnable 1'b1
`define ReadDisable 1'b0
`define ChipEnable 1'b1
`define ChipDisable 1'b0

// bus
`define InstBus 31:0
`define InstAddrBus 31:0
`define RegAddrBus 4:0
`define RegBus 31:0
`define AluOpBus 7:0

// common regs
`define RegNum 32        // reg num
`define RegNumLog2 5

// data size
`define Word 3'h1
// RV32I inst num
//`define LUI 8'h0
//`define AUIPC 8'h1
//`define JAL 8'h2
//`define JALR 8'h3
//`define BEQ 8'h4
//`define BNE 8'h5
//`define BLT 8'h6
//`define BGE 8'h7
//`define BLTU 8'h8
//`define BGEU 8'h9
//`define LB 8'ha
//`define LH 8'hb
//`define LW 8'hc
//`define LBU 8'hd
//`define LHU 8'he
//`define SB 8'hf
//`define SH 8'h10
//`define SW 8'h11
//`define ADDI 8'h12
//`define SLTI 8'h13
//`define SLTIU 8'h14
//`define XORI 8'h15
`define ORI 8'h16
//`define ANDI 8'h17
//`define SLLI 8'h18
//`define SRLI 8'h19
//`define SRAI 8'h1a
//`define ADD 8'h1b
//`define SUB 8'h1c
//`define SLL 8'h1d
//`define SLT 8'h1e
//`define SLTU 8'h1f
//`define XOR 8'h20
//`define SRL 8'h21
//`define SRA 8'h22
//`define OR 8'h23
//`define AND 8'h24
//`define FENCE 8'h25
//`define ECALL 8'h26
//`define EBREAK 8'h27

// M  extension
//`define MUL 8'h28
//`define MULH 8'h29
//`define MULHSU 8'h2a
//`define MULHU 8'h2b
//`define DIV 8'h2c
//`define DIVU 8'h2d
//`define REM 8'h2e
//`define REMU 8'h2f

`define NOP 8'h12   //addi x0,x0,0



// I type inst
`define INST_TYPE_I 7'b0010011
`define INST_ORI    3'b110

iftest/pc_reg.v
/*
This file is for PC module
    - variable end up with 'i' is for input and 'o' is for output.
    - clk_i represent clock
    - rst_i represent reset
    - pc_o represent PC register(Program counter)
        the PC here is 6bit width
    - ce_o is 
*/
`include "defines.v"


module pc_reg (
    input wire clk_i,
    input wire rst_i,
    output reg[`InstAddrBus] pc_o,
    output reg ce_o
);
    always @(posedge clk_i) begin
        // if reset enable, then Chip disable
        if (rst_i == `RstEnable) begin
            ce_o <= `ChipDisable;
        end else begin
            ce_o <= `ChipEnable;
        end
    end

    always @(posedge clk_i) begin
        if (ce_o == `ChipEnable) begin
            pc_o <= pc_o + `Word;
        end else begin
            pc_o <= `CpuResetAddr;
        end
    end
    
endmodule

iftest/inst_fetch.v
//`include "rom.v"
//`include "pc_reg.v"

module inst_fetch (
    input wire rst_i,
    input wire clk_i,
    output wire[31:0] inst_o
);
    wire[31:0] pc_wire;
    wire ce_wire;

    pc_reg pc_reg0(
        .rst_i(rst_i),
        .clk_i(clk_i),
        .pc_o(pc_wire),
        .ce_o(ce_wire)
    );

    rom rom0(
        .addr_i(pc_wire),
        .ce_i(ce_wire),
        .inst_o(inst_o)
    );
endmodule

dev/testing_module.v
//`include "inst_fetch.v"

module inst_fetch_tb;
    reg CLOCK;
    reg rst;
    wire[31:0] inst;

    initial begin
        CLOCK = 1'b0;
        forever #10 CLOCK = ~CLOCK;
    end

    initial begin
        $dumpfile("debug.vcd");
        $dumpvars(1);
        rst = 1'b1;

        #200 rst = 1'b0;
        #900 $finish;
        #1000 $stop;
    end

    inst_fetch inst_fetch_tb(
        .clk_i(CLOCK),
        .rst_i(rst),
        .inst_o(inst)
    );
endmodule

iftest/debug.vcd
$date
	Mon Apr  4 16:26:56 2022
$end
$version
	Icarus Verilog
$end
$timescale
	1s
$end
$scope module inst_fetch_tb $end
$var wire 32 ! inst [31:0] $end
$var reg 1 " CLOCK $end
$var reg 1 # rst $end
$upscope $end
$enddefinitions $end
#0
$dumpvars
1#
0"
b0 !
$end
#10
b100000001 !
1"
#20
0"
#30
b1000000010 !
1"
#40
0"
#50
b1100000011 !
1"
#60
0"
#70
b10000000100 !
1"
#80
0"
#90
b10100000101 !
1"
#100
0"
#110
bx !
1"
#120
0"
#130
1"
#140
0"
#150
1"
#160
0"
#170
1"
#180
0"
#190
1"
#200
0"
0#
#210
b0 !
1"
