multiplier/defines.v
`define CpuResetAddr 32'h0

`define RstEnable 1'b0
`define RstDisable 1'b1
`define ZeroWord 32'h0
`define ZeroReg 5'h0
`define WriteEnable 1'b1
`define WriteDisable 1'b0
`define ReadEnable 1'b1
`define ReadDisable 1'b0
`define ChipEnable 1'b1
`define ChipDisable 1'b0

// bus
`define InstBus 31:0
`define InstAddrBus 31:0
`define RegAddrBus 4:0
`define RegBus 31:0
`define AluOpBus 7:0

// temp
`define HalfRegBus 15:0

// common regs
`define RegNum 32        // reg num
`define RegNumLog2 5

// data size
`define Word 3'h1
// RV32I inst num
//`define LUI 8'h0
//`define AUIPC 8'h1
//`define JAL 8'h2
//`define JALR 8'h3
//`define BEQ 8'h4
//`define BNE 8'h5
//`define BLT 8'h6
//`define BGE 8'h7
//`define BLTU 8'h8
//`define BGEU 8'h9
//`define LB 8'ha
//`define LH 8'hb
//`define LW 8'hc
//`define LBU 8'hd
//`define LHU 8'he
//`define SB 8'hf
//`define SH 8'h10
//`define SW 8'h11
//`define ADDI 8'h12
//`define SLTI 8'h13
//`define SLTIU 8'h14
//`define XORI 8'h15
`define ORI 8'h16
//`define ANDI 8'h17
//`define SLLI 8'h18
//`define SRLI 8'h19
//`define SRAI 8'h1a
//`define ADD 8'h1b
//`define SUB 8'h1c
//`define SLL 8'h1d
//`define SLT 8'h1e
//`define SLTU 8'h1f
//`define XOR 8'h20
//`define SRL 8'h21
//`define SRA 8'h22
//`define OR 8'h23
//`define AND 8'h24
//`define FENCE 8'h25
//`define ECALL 8'h26
//`define EBREAK 8'h27

// M  extension
//`define MUL 8'h28
//`define MULH 8'h29
//`define MULHSU 8'h2a
//`define MULHU 8'h2b
//`define DIV 8'h2c
//`define DIVU 8'h2d
//`define REM 8'h2e
//`define REMU 8'h2f

`define NOP 8'h12   //addi x0,x0,0



// I type inst
`define INST_TYPE_I 7'b0010011
`define INST_ORI    3'b110

last semester/multiplier/self32.v
/*
先決條件：這裡不管 adder 是使用 RCA 還是 carry look ahead，因為太複雜了。所以直接讓 verilog 自己做加法。

實現結果：有號的數字相乘，使用循序電路實做，非邏輯電路。

想法：將所有數字轉換回正數後相乘，最後在依照結果決定要不要做補數。

優點：簡單易懂

缺點：相較 booth's 演算法較沒有效率。相較邏輯電路更慢。

改進：應該有辦法跳過 bit 是 0 的位元做運算，這樣就不用 16 個 clock 了。
    實際運作的地方大兩使用到 blocking statement，可能有改進的地方。
*/
`include "defines.v"

module Multiplier(
    input wire clk,
    input wire rst,
    input wire[15:0] A_i,
    input wire[15:0] B_i,

    output reg[31:0] C_o
);
    reg[15:0] A_comp, B_comp;
    reg[3:0] counter;
    reg[15:0] adder_o;
    reg complete;

    always @(posedge clk) begin
        /* 決定要不要補數 */
        if(A_i[15] == 1) begin
            A_comp = ~A_i + 1;
        end else begin
            A_comp = A_i;
        end

        if(B_i[15] == 1) begin
            B_comp = ~B_i + 1;
        end else begin
            B_comp = B_i;
        end

        /* 乘法器運實際運作的地方，大量運用到 blocking statement */
        if (rst == `RstEnable) begin
            C_o <= 32'h0;
            adder_o <= 16'h0;
            counter <= 4'h0;
            complete <= 1'b0;
        end else if(complete == 0) begin
            if(counter == 0) begin
                C_o <= {{16{1'b0}}, B_comp};
                counter <= counter + 1;
            end else begin
                adder_o = (A_comp & {16{C_o[0]}}) + C_o[31:16];
                C_o[31:16] = adder_o;
                C_o = C_o >> 1;

                if(counter == 4'hf) begin
                    complete = 1'b1;
                    C_o = C_o >> 1;
                    if(A_i[15] ^ B_i[15]) begin
                        C_o = ~C_o + 1;
                    end else begin
                        C_o = C_o;
                    end
                end else begin
                    counter = counter + 1;
                end
            end
        end else begin
            complete <= complete;
            counter <= counter;
            adder_o <= adder_o;
        end
    end

endmodule

multiplier/testbench.v
`timescale 1ns/1ps

module testbench();
    
    reg CLOCK;
    reg rst;
    reg[15:0] A = -16'b010;
    reg[15:0] B = 16'b1110;
    wire[31:0] out;
    
    initial begin
        CLOCK = 1'b0;
        forever #10 CLOCK = ~CLOCK;
    end

    initial begin
        $dumpfile("debug.vcd");
        $dumpvars(1);
        #0 rst = 1'b0;
        #200 rst = 1'b1;
        #900 $finish;
        #1000 $stop;
    end
    
    Multiplier M(
        .clk(CLOCK),
        .rst(rst),
        .A_i( A),
        .B_i(B),
        .C_o(out)
    );
    
endmodule

multiplier/debug.vcd
$date
	Tue Apr  5 12:02:26 2022
$end
$version
	Icarus Verilog
$end
$timescale
	1ps
$end
$scope module testbench $end
$var wire 32 ! out [31:0] $end
$var reg 16 " A [15:0] $end
$var reg 16 # B [15:0] $end
$var reg 1 $ CLOCK $end
$var reg 1 % rst $end
$upscope $end
$enddefinitions $end
#0
$dumpvars
0%
0$
b1110 #
b1111111111111110 "
bx !
$end
#10000
b0 !
1$
#20000
0$
#30000
1$
#40000
0$
#50000
1$
#60000
0$
#70000
1$
#80000
0$
#90000
1$
#100000
0$
#110000
1$
#120000
0$
#130000
1$
#140000
0$
#150000
1$
#160000
0$
#170000
1$
#180000
0$
#190000
1$
#200000
0$
1%
#210000
b1110 !
1$
#220000
0$
#230000
b111 !
1$
#240000
0$
#250000
b10000000000000011 !
1$
#260000
0$
#270000
b11000000000000001 !
1$
#280000
0$
#290000
b11100000000000000 !
1$
#300000
0$
#310000
b1110000000000000 !
1$
#320000
0$
#330000
b111000000000000 !
1$
#340000
0$
#350000
b11100000000000 !
1$
#360000
0$
#370000
b1110000000000 !
1$
#380000
0$
#390000
b111000000000 !
1$
#400000
0$
#410000
b11100000000 !
1$
#420000
0$
#430000
b1110000000 !
1$
#440000
0$
#450000
b111000000 !
1$
#460000
0$
#470000
b11100000 !
1$
#480000
0$
#490000
b1110000 !
1$
#500000
0$
#510000
b11111111111111111111111111100100 !
1$
